{"dependencies":[{"name":"/media/chiki/F85E0E485E0DFFDC/imooc/movie-trailer/package.json","includedInParent":true,"mtime":1530353022696},{"name":"./index.js","dynamic":true,"parent":"/media/chiki/F85E0E485E0DFFDC/imooc/movie-trailer/src/index.html","resolved":"/media/chiki/F85E0E485E0DFFDC/imooc/movie-trailer/src/index.js"}],"generated":{"html":"<!DOCTYPE html>\n<html lang=\"en\">\n<head>\n    <meta charset=\"UTF-8\">\n    <meta name=\"viewport\" content=\"width=device-width, initial-scale=1.0\">\n    <meta http-equiv=\"X-UA-Compatible\" content=\"ie=edge\">\n    <title>黑骑预告片网站</title>\n</head>\n<body>\n    <div id=\"app\"></div>    \n    <script src=\"https://cdn.bootcss.com/jquery/3.3.1/jquery.min.js\"></script>\n    <script src=\"/2e15fe5790e5017d270e300e4c48e721.js\"></script>\n</body>\n</html>"},"hash":"294f9a46d8d50a5b98cba06bc3b531d0","cacheData":{},"id":1}